dataclassmodule/__init__.py
dataclassmodule/dataclassmodule.py
dataclassmodule-0.1.1.dist-info/WHEEL
dataclassmodule-0.1.1.dist-info/METADATA
dataclassmodule-0.1.1.dist-info/RECORD
